realstarexx/__init__.py
realstarexx/core.py
realstarexx-1.0.2.dist-info/licenses/LICENSE
realstarexx-1.0.2.dist-info/METADATA
realstarexx-1.0.2.dist-info/WHEEL
realstarexx-1.0.2.dist-info/top_level.txt
realstarexx-1.0.2.dist-info/RECORD
