Metadata-Version: 2.4
Name: realstarexx
Version: 1.0.2
Summary: Coding and programming isn't same
Home-page: https://github.com/realstarexx/starexx
Author: Ankit Mehta
Author-email: starexx.m@gmail.com
Classifier: Programming Language :: Python :: 3
Classifier: License :: OSI Approved :: MIT License
Classifier: Operating System :: OS Independent
Requires-Python: >=3.6
License-File: LICENSE
Dynamic: author
Dynamic: author-email
Dynamic: classifier
Dynamic: description
Dynamic: description-content-type
Dynamic: home-page
Dynamic: license-file
Dynamic: requires-python
Dynamic: summary
